{"assets":{"53EE076C5EB15D7C98735110F532369A":{"type":"texture","index":10,"assetRequest":{"type":"slide","state":"outgoing","slide":"CA1ECB27-0CA7-4520-9141-86896300DEA5"},"url":"assets/53EE076C5EB15D7C98735110F532369A.svg","width":1024,"height":768},"A0370CEF21B013E107746A0E90DE5015":{"type":"texture","index":11,"assetRequest":{"type":"slide","state":"incoming","slide":"6911AE3A-0300-498E-B581-C6DAE68656E8"},"url":"assets/A0370CEF21B013E107746A0E90DE5015.svg","width":1024,"height":768}},"events":[{"effects":[{"beginTime":0,"baseLayer":{"animations":[],"initialState":{"affineTransform":[1,0,0,1,0,0],"masksToBounds":true,"rotation":0,"scale":1,"position":{"pointX":512,"pointY":384},"width":1024,"sublayerTransform":[1,0,0,0,0,1,0,0,0,0,1,0,0,0,0,1],"contentsRect":{"y":0,"x":0,"width":1,"height":1},"opacity":1,"edgeAntialiasingMask":0,"height":768,"hidden":false,"anchorPoint":{"pointX":0.5,"pointY":0.5}},"objectID":"0","layers":[{"animations":[],"initialState":{"affineTransform":[1,0,0,1,0,0],"masksToBounds":false,"rotation":0,"scale":1,"position":{"pointX":512,"pointY":384},"width":1024,"sublayerTransform":[1,0,0,0,0,1,0,0,0,0,1,-0.0004922987690640373,0,0,0,1],"contentsRect":{"y":0,"x":0,"width":1,"height":1},"opacity":1,"edgeAntialiasingMask":15,"height":768,"hidden":false,"anchorPoint":{"pointX":0.5,"pointY":0.5}},"layers":[{"animations":[],"layers":[],"initialState":{"affineTransform":[1,0,0,1,0,0],"masksToBounds":false,"rotation":0,"scale":1,"position":{"pointX":512,"pointY":384},"width":1024,"sublayerTransform":[1,0,0,0,0,1,0,0,0,0,1,0,0,0,0,1],"contentsRect":{"y":0,"x":0,"width":1,"height":1},"opacity":1,"edgeAntialiasingMask":0,"height":768,"hidden":false,"anchorPoint":{"pointX":0.5,"pointY":0.5}},"texture":"A0370CEF21B013E107746A0E90DE5015"},{"animations":[{"from":{"scalar":false},"beginTime":0,"repeatCount":0,"fillMode":"both","property":"hidden","duration":0.01,"to":{"scalar":true}}],"layers":[],"initialState":{"affineTransform":[1,0,0,1,0,0],"masksToBounds":false,"rotation":0,"scale":1,"position":{"pointX":512,"pointY":384},"width":1024,"sublayerTransform":[1,0,0,0,0,1,0,0,0,0,1,0,0,0,0,1],"contentsRect":{"y":0,"x":0,"width":1,"height":1},"opacity":1,"edgeAntialiasingMask":0,"height":768,"hidden":false,"anchorPoint":{"pointX":0.5,"pointY":0.5}},"texture":"53EE076C5EB15D7C98735110F532369A"}]}]},"effects":[],"duration":0.01,"type":"transition","name":"none","objectID":"0"}],"automaticPlay":false,"hyperlinks":[],"accessibility":[{"text":"1/10G","targetRectangle":{"y":573.0286862850189,"x":524.0555918216705,"width":65.37599999999998,"height":29}},{"text":"cloud.pdf","targetRectangle":{"y":2.668962941082469,"x":641.946899108625,"width":298.8550993352402,"height":271.4546289731818}},{"text":"Server","targetRectangle":{"y":651.0114135742188,"x":477.332,"width":69.33600000000001,"height":29}},{"text":"Agg2 (aggregation switch)","targetRectangle":{"y":312.0804138183594,"x":163.4935645751953,"width":144.936,"height":87}},{"text":"10/40G","targetRectangle":{"y":418.0631711483002,"x":517.3835909366608,"width":78.72000000000003,"height":29}},{"text":"10/40G","targetRectangle":{"y":316.571685552597,"x":331.8614962100983,"width":78.72000000000003,"height":29}},{"text":"IP Router","targetRectangle":{"y":341.0804138183594,"x":742.0184506835938,"width":98.71199999999999,"height":29}},{"text":"The Internet","targetRectangle":{"y":109.3477663993835,"x":689.8324990272522,"width":192.78,"height":43}},{"text":"Agg3 (aggregation switch)","targetRectangle":{"y":142.9278869628906,"x":163.4935645751953,"width":144.936,"height":87}},{"text":"10/40G","targetRectangle":{"y":324.7564389705658,"x":613.4185030460358,"width":78.72000000000003,"height":29}},{"text":"10/40G","targetRectangle":{"y":256.0041501522064,"x":242.374374628067,"width":78.72000000000003,"height":29}},{"text":"10/40/100G","targetRectangle":{"y":256.0041501522064,"x":794.1407856941223,"width":125.424,"height":29}},{"text":"TOR","targetRectangle":{"y":467.0458984375,"x":487.988,"width":48.02399999999994,"height":29}},{"text":"(top-of-rack switch)","targetRectangle":{"y":496.0458984375,"x":449.324,"width":132.0239999999999,"height":58}},{"text":"50 Mb/s per server","targetRectangle":{"y":544.5286866426468,"x":662.0048401870728,"width":304.056,"height":43}},{"text":"= 2,000 servers","targetRectangle":{"y":587.5286866426468,"x":688.1048401870728,"width":251.856,"height":43}},{"text":"￼","targetRectangle":{"y":732.5,"x":506.4959999024868,"width":10.00800000000004,"height":22}},{"text":"Agg1","targetRectangle":{"y":312.0804138183594,"x":482.66,"width":58.68000000000006,"height":29}},{"text":"(aggregation switch)","targetRectangle":{"y":341.0804138183594,"x":442.868,"width":144.936,"height":58}}],"baseLayer":{"animations":[],"initialState":{"affineTransform":[1,0,0,1,0,0],"masksToBounds":true,"rotation":0,"scale":1,"position":{"pointX":512,"pointY":384},"width":1024,"sublayerTransform":[1,0,0,0,0,1,0,0,0,0,1,0,0,0,0,1],"contentsRect":{"y":0,"x":0,"width":1,"height":1},"opacity":1,"edgeAntialiasingMask":0,"height":768,"hidden":false,"anchorPoint":{"pointX":0.5,"pointY":0.5}},"objectID":"0","layers":[{"animations":[],"initialState":{"affineTransform":[1,0,0,1,0,0],"masksToBounds":false,"rotation":0,"scale":1,"position":{"pointX":512,"pointY":384},"width":1024,"sublayerTransform":[1,0,0,0,0,1,0,0,0,0,1,-0.0004922987690640373,0,0,0,1],"contentsRect":{"y":0,"x":0,"width":1,"height":1},"opacity":1,"edgeAntialiasingMask":15,"height":768,"hidden":false,"anchorPoint":{"pointX":0.5,"pointY":0.5}},"layers":[{"animations":[],"layers":[],"initialState":{"affineTransform":[1,0,0,1,0,0],"masksToBounds":false,"rotation":0,"scale":1,"position":{"pointX":512,"pointY":384},"width":1024,"sublayerTransform":[1,0,0,0,0,1,0,0,0,0,1,0,0,0,0,1],"contentsRect":{"y":0,"x":0,"width":1,"height":1},"opacity":1,"edgeAntialiasingMask":0,"height":768,"hidden":false,"anchorPoint":{"pointX":0.5,"pointY":0.5}},"texture":"53EE076C5EB15D7C98735110F532369A"}]}]}}]}